pisces/__init__.py
pisces/command.py
pisces/main.py
pisces/tools/chromedriver.exe
pisces/tools/chromedriver_linux
pisces/tools/chromedriver_mac
python_pisces-0.0.5.dist-info/METADATA
python_pisces-0.0.5.dist-info/RECORD
python_pisces-0.0.5.dist-info/WHEEL
python_pisces-0.0.5.dist-info/entry_points.txt
python_pisces-0.0.5.dist-info/top_level.txt
