Metadata-Version: 2.1
Name: python-pisces
Version: 0.0.5
Summary: Use keywords to search for and download images.
Home-page: https://github.com/wolfhong/python-pisces
Author: wolfhong
Author-email: hongxucai1991@gmail.com
License: MIT
Keywords: download-images,search-images,algorithm-training,image-dataset,google,baidu
Platform: any
Classifier: License :: OSI Approved :: MIT License
Classifier: Programming Language :: Python
Classifier: Programming Language :: Python :: 2
Classifier: Programming Language :: Python :: 3
Classifier: Development Status :: 4 - Beta
Classifier: Intended Audience :: Developers
Classifier: Topic :: Software Development :: Libraries
Classifier: Topic :: Utilities
Classifier: Operating System :: Microsoft :: Windows
Classifier: Operating System :: POSIX :: Linux
Classifier: Operating System :: MacOS :: MacOS X
Requires-Python: >=2.7, <4
Requires-Dist: selenium (>=3.8.0)
Requires-Dist: requests
